CHANGES.txt
LICENSE.txt
MANIFEST.in
setup.cfg
setup.py
canonicalwebteam/__init__.py
canonicalwebteam.get_feeds.egg-info/PKG-INFO
canonicalwebteam.get_feeds.egg-info/SOURCES.txt
canonicalwebteam.get_feeds.egg-info/dependency_links.txt
canonicalwebteam.get_feeds.egg-info/requires.txt
canonicalwebteam.get_feeds.egg-info/top_level.txt
canonicalwebteam/get_feeds/__init__.py
canonicalwebteam/get_feeds/templatetags.py