Metadata-Version: 1.0
Name: canonicalwebteam.get-feeds
Version: 0.2.3
Summary: Functions and template tags for retrieving JSON or RSS feed content.
Home-page: https://github.com/canonical-webteam/get-feeds
Author: Canonical Webteam
Author-email: UNKNOWN
License: UNKNOWN
Platform: UNKNOWN
